MANIFEST.in
README.txt
setup.py
bise/__init__.py
bise.theme.egg-info/PKG-INFO
bise.theme.egg-info/SOURCES.txt
bise.theme.egg-info/dependency_links.txt
bise.theme.egg-info/entry_points.txt
bise.theme.egg-info/namespace_packages.txt
bise.theme.egg-info/not-zip-safe
bise.theme.egg-info/requires.txt
bise.theme.egg-info/top_level.txt
bise/theme/__init__.py
bise/theme/configure.zcml
bise/theme/patches.py
bise/theme/profiles.zcml
bise/theme/rebuild_i18n.sh
bise/theme/setuphandlers.py
bise/theme/skins.zcml
bise/theme/syndication.py
bise/theme/tests.py
bise/theme/unconfigure.zcml
bise/theme/upgrades.py
bise/theme/upgrades.zcml
bise/theme/behaviors/__init__.py
bise/theme/behaviors/configure.zcml
bise/theme/behaviors/sources.py
bise/theme/behaviors/tagging.py
bise/theme/browser/__init__.py
bise/theme/browser/configure.zcml
bise/theme/browser/creators.py
bise/theme/browser/feed.py
bise/theme/browser/glossary.py
bise/theme/browser/glossarydefinition.py
bise/theme/browser/importnews.py
bise/theme/browser/importstories.py
bise/theme/browser/interfaces.py
bise/theme/browser/logo.pt
bise/theme/browser/path_bar.pt
bise/theme/browser/personal_bar.pt
bise/theme/browser/sections.pt
bise/theme/browser/sitetitle.py
bise/theme/browser/sunburstview.py
bise/theme/browser/viewlets.py
bise/theme/browser/template-overrides/CONTENTS.txt
bise/theme/browser/template-overrides/Products.ATVocabularyManager.skins.ATVocabularyManager.vocabularytool_view.cpt
bise/theme/browser/template-overrides/Products.Collage.browser.templates.collage_view.pt
bise/theme/browser/template-overrides/Products.feedfeeder.browser.feed-folder.pt
bise/theme/browser/template-overrides/plone.portlet.collection.collection.pt
bise/theme/browser/templates/CONTENTS.txt
bise/theme/browser/templates/glossarydefinitionview.pt
bise/theme/browser/templates/glossaryview.pt
bise/theme/browser/templates/rss_summary_view.pt
bise/theme/locales/bise.theme-manual.pot
bise/theme/locales/bise.theme.pot
bise/theme/locales/plone.pot
bise/theme/locales/en/LC_MESSAGES/bise.theme.po
bise/theme/locales/en/LC_MESSAGES/plone.po
bise/theme/profiles/default/actions.xml
bise/theme/profiles/default/bise.theme_various.txt
bise/theme/profiles/default/cssregistry.xml
bise/theme/profiles/default/diff_tool.xml
