Metadata-Version: 1.1
Name: bise.theme
Version: 1.20.1
Summary: Installable theme: bise.theme
Home-page: https://github.com/eea/bise.theme
Author: CodeSyntax & Bilbomatica
Author-email: mlarreategi@codesyntax.com
License: GPL
Platform: UNKNOWN
Classifier: Framework :: Plone
Classifier: Programming Language :: Python
